consul_utils/__init__.py
consul_utils/application.py
consul_utils/commands.py
consul_utils/exceptions.py
consul_utils/filters.py
consul_utils/patsnap.py
consul_utils/reporter.py
consul_utils/search.py
consul_utils-0.1.3.dist-info/METADATA
consul_utils-0.1.3.dist-info/WHEEL
consul_utils-0.1.3.dist-info/entry_points.txt
consul_utils-0.1.3.dist-info/top_level.txt
consul_utils-0.1.3.dist-info/RECORD
