Metadata-Version: 2.1
Name: consul-utils
Version: 0.1.3
Summary: Useful tools to handle Consul.
Home-page: https://github.com/wwtg99/consul_utils
Author: wuwentao
Author-email: wwtg99@126.com
License: MIT
Keywords: consul,key_value,search,diff
Platform: UNKNOWN
Classifier: Operating System :: OS Independent
Classifier: License :: OSI Approved :: MIT License
Classifier: Programming Language :: Python :: 3.5
Classifier: Programming Language :: Python :: 3.6
Classifier: Programming Language :: Python :: 3.7
Requires-Python: >=3.5
Requires-Dist: hsettings (>=0.1)
Requires-Dist: python-consul
Requires-Dist: click
Requires-Dist: colorama
Requires-Dist: diskcache
